README.md
pyproject.toml
setup.py
deeporigin_molstar/__init__.py
deeporigin_molstar.egg-info/PKG-INFO
deeporigin_molstar.egg-info/SOURCES.txt
deeporigin_molstar.egg-info/dependency_links.txt
deeporigin_molstar.egg-info/requires.txt
deeporigin_molstar.egg-info/top_level.txt
deeporigin_molstar/src/__init__.py
deeporigin_molstar/src/display.py
deeporigin_molstar/src/jupyter_viewer.py
deeporigin_molstar/src/utils.py
deeporigin_molstar/src/viewers/__init__.py
deeporigin_molstar/src/viewers/docking_viewer.py
deeporigin_molstar/src/viewers/molecule_viewer.py
deeporigin_molstar/src/viewers/protein_viewer.py
deeporigin_molstar/src/viewers/viewer.py
tests/test_docking_viewer.py
tests/test_readme_examples.py