Metadata-Version: 2.4
Name: deeporigin_molstar
Version: 0.1.1
Summary: deeporigin_molstar
Author: deeporigin
Requires-Dist: rdkit
Requires-Dist: IPython
Provides-Extra: test
Requires-Dist: pytest>=7; extra == "test"
Requires-Dist: ruff; extra == "test"
Requires-Dist: interrogate; extra == "test"
Dynamic: author
Dynamic: description
Dynamic: description-content-type
Dynamic: provides-extra
Dynamic: requires-dist
Dynamic: summary
